CHANGES.rst
CONTRIBUTORS.rst
MANIFEST.in
README.rst
setup.py
docs/LICENSE.GPL
docs/LICENSE.txt
src/interlegis/__init__.py
src/interlegis.portalmodelo.buscadores.egg-info/PKG-INFO
src/interlegis.portalmodelo.buscadores.egg-info/SOURCES.txt
src/interlegis.portalmodelo.buscadores.egg-info/dependency_links.txt
src/interlegis.portalmodelo.buscadores.egg-info/entry_points.txt
src/interlegis.portalmodelo.buscadores.egg-info/namespace_packages.txt
src/interlegis.portalmodelo.buscadores.egg-info/not-zip-safe
src/interlegis.portalmodelo.buscadores.egg-info/requires.txt
src/interlegis.portalmodelo.buscadores.egg-info/top_level.txt
src/interlegis/portalmodelo/__init__.py
src/interlegis/portalmodelo/buscadores/__init__.py
src/interlegis/portalmodelo/buscadores/config.py
src/interlegis/portalmodelo/buscadores/configure.zcml
src/interlegis/portalmodelo/buscadores/interfaces.py
src/interlegis/portalmodelo/buscadores/profiles.zcml
src/interlegis/portalmodelo/buscadores/testing.py
src/interlegis/portalmodelo/buscadores/browser/__init__.py
src/interlegis/portalmodelo/buscadores/browser/base.py
src/interlegis/portalmodelo/buscadores/browser/buscaleg.pt
src/interlegis/portalmodelo/buscadores/browser/buscaleg.py
src/interlegis/portalmodelo/buscadores/browser/configure.zcml
src/interlegis/portalmodelo/buscadores/browser/lexml.pt
src/interlegis/portalmodelo/buscadores/browser/lexml.py
src/interlegis/portalmodelo/buscadores/locales/interlegis.portalmodelo.buscadores.pot
src/interlegis/portalmodelo/buscadores/locales/manual.pot
src/interlegis/portalmodelo/buscadores/locales/plone.pot
src/interlegis/portalmodelo/buscadores/locales/pt_BR/LC_MESSAGES/interlegis.portalmodelo.buscadores.po
src/interlegis/portalmodelo/buscadores/locales/pt_BR/LC_MESSAGES/plone.po
src/interlegis/portalmodelo/buscadores/portlets/__init__.py
src/interlegis/portalmodelo/buscadores/portlets/buscaleg.pt
src/interlegis/portalmodelo/buscadores/portlets/buscaleg.py
src/interlegis/portalmodelo/buscadores/portlets/configure.zcml
src/interlegis/portalmodelo/buscadores/portlets/lexml.pt
src/interlegis/portalmodelo/buscadores/portlets/lexml.py
src/interlegis/portalmodelo/buscadores/profiles/default/browserlayer.xml
src/interlegis/portalmodelo/buscadores/profiles/default/metadata.xml
src/interlegis/portalmodelo/buscadores/profiles/default/portlets.xml
src/interlegis/portalmodelo/buscadores/profiles/uninstall/interlegis.portalmodelo.buscadores.txt
src/interlegis/portalmodelo/buscadores/static/images/buscaleg-mini.png
