Metadata-Version: 2.1
Name: interlegis.portalmodelo.buscadores
Version: 1.0rc5
Summary: Integração do Portal Modelo com buscadores externos.
Home-page: https://github.com/interlegis/interlegis.portalmodelo.buscadores
Author: Programa Interlegis
Author-email: ti@interlegis.leg.br
License: UNKNOWN
Keywords: interlegis portalmodelo lexml search plone
Platform: UNKNOWN
Classifier: Development Status :: 4 - Beta
Classifier: Environment :: Web Environment
Classifier: Framework :: Plone
Classifier: Framework :: Plone :: 4.3
Classifier: Intended Audience :: System Administrators
Classifier: License :: OSI Approved :: GNU General Public License v2 (GPLv2)
Classifier: Operating System :: OS Independent
Classifier: Programming Language :: Python
Classifier: Programming Language :: Python :: 2.7
Classifier: Topic :: Software Development :: Libraries :: Python Modules
Provides-Extra: test
